diffqc/__init__.py
diffqc/_operators.py
diffqc/common.py
diffqc/dense.py
diffqc/lib.py
diffqc/nn.py
diffqc/pennylane.py
diffqc/sparse.py
diffqc/util.py
diffqc-0.0.2.dist-info/LICENSE
diffqc-0.0.2.dist-info/METADATA
diffqc-0.0.2.dist-info/WHEEL
diffqc-0.0.2.dist-info/entry_points.txt
diffqc-0.0.2.dist-info/top_level.txt
diffqc-0.0.2.dist-info/RECORD
