Metadata-Version: 2.1
Name: diffqc
Version: 0.0.2
Summary: Diiferentiable Quantum Simulator
Home-page: https://github.com/ymd-h/diffqc
Author: H. Yamada
License: UNKNOWN
Project-URL: Bug Report & QA, https://github.com/ymd-h/diffqc/discussions
Platform: UNKNOWN
Classifier: License :: OSI Approved :: MIT License
Classifier: Programming Language :: Python :: 3
Classifier: Topic :: Scientific/Engineering
License-File: LICENSE
Requires-Dist: jax
Requires-Dist: jaxlib
Provides-Extra: example
Requires-Dist: flax ; extra == 'example'
Requires-Dist: optax ; extra == 'example'
Requires-Dist: scikit-learn ; extra == 'example'
Requires-Dist: tqdm ; extra == 'example'
Provides-Extra: pennylane
Requires-Dist: pennylane ; extra == 'pennylane'
Provides-Extra: test
Requires-Dist: coverage ; extra == 'test'
Requires-Dist: unittest-xml-reporting ; extra == 'test'
Requires-Dist: numpy ; extra == 'test'
